libcdt1/__init__.py
libcdt1/install/bin/cadet-cli
libcdt1/install/bin/convertFile
libcdt1/install/bin/createConvBenchmark
libcdt1/install/bin/createLWE
libcdt1/install/bin/createMCLin
libcdt1/install/bin/createSCLang
libcdt1/install/bin/createSCLin
libcdt1/install/bin/createSCLinStep
libcdt1/install/include/cadet/Exceptions.hpp
libcdt1/install/include/cadet/ExternalFunction.hpp
libcdt1/install/include/cadet/FactoryFuncs.hpp
libcdt1/install/include/cadet/HashUtil.hpp
libcdt1/install/include/cadet/InletProfile.hpp
libcdt1/install/include/cadet/LibExportImport.hpp
libcdt1/install/include/cadet/LibVersionInfo.hpp
libcdt1/install/include/cadet/Logging.hpp
libcdt1/install/include/cadet/Model.hpp
libcdt1/install/include/cadet/ModelBuilder.hpp
libcdt1/install/include/cadet/ModelSystem.hpp
libcdt1/install/include/cadet/Notification.hpp
libcdt1/install/include/cadet/ParameterId.hpp
libcdt1/install/include/cadet/ParameterProvider.hpp
libcdt1/install/include/cadet/Simulator.hpp
libcdt1/install/include/cadet/SolutionExporter.hpp
libcdt1/install/include/cadet/SolutionRecorder.hpp
libcdt1/install/include/cadet/StringUtil.hpp
libcdt1/install/include/cadet/StrongTypes.hpp
libcdt1/install/include/cadet/cadet.h
libcdt1/install/include/cadet/cadet.hpp
libcdt1/install/include/cadet/cadetCompilerInfo.hpp
libcdt1/install/lib/libcadet.so
libcdt1/install/lib/libcadet.so.0
libcdt1/install/lib/libcadet.so.5.0.1
libcdt1/install/lib/libcadet_nonlinalg_static.a
libcdt1/install/lib/libcadet_static.a
libcdt1-1.0.2.dist-info/METADATA
libcdt1-1.0.2.dist-info/WHEEL
libcdt1-1.0.2.dist-info/top_level.txt
libcdt1-1.0.2.dist-info/RECORD
