Metadata-Version: 2.2
Name: libcdt1
Version: 1.0.2
Summary: libcdt1
Author: Shobhith
Classifier: Programming Language :: Python :: 3
Classifier: Operating System :: OS Independent
Dynamic: author
Dynamic: classifier
Dynamic: summary
